README.txt
setup.cfg
setup.py
AdjectorTracPlugin.egg-info/PKG-INFO
AdjectorTracPlugin.egg-info/SOURCES.txt
AdjectorTracPlugin.egg-info/dependency_links.txt
AdjectorTracPlugin.egg-info/entry_points.txt
AdjectorTracPlugin.egg-info/namespace_packages.txt
AdjectorTracPlugin.egg-info/requires.txt
AdjectorTracPlugin.egg-info/top_level.txt
adjector/__init__.py
adjector/plugins/__init__.py
adjector/plugins/trac/__init__.py
adjector/plugins/trac/adjector_trac.py