Metadata-Version: 1.0
Name: AdjectorTracPlugin
Version: 1.0b2
Summary: Integrate Adjector into your trac installation: render zones in trac templates.
Home-page: http://projects.icapsid.net/adjector
Author: David Isaacson
Author-email: david@icapsid.net
License: GPL v2 or v3, at your option
Platform: UNKNOWN
